chattr_req2toml/__init__.py
chattr_req2toml/console.py
chattr_req2toml/utils.py
chattr_req2toml-1.1.1.dist-info/entry_points.txt
chattr_req2toml-1.1.1.dist-info/LICENSE
chattr_req2toml-1.1.1.dist-info/WHEEL
chattr_req2toml-1.1.1.dist-info/METADATA
chattr_req2toml-1.1.1.dist-info/RECORD
