Metadata-Version: 2.1
Name: chattr-req2toml
Version: 1.1.1
Summary: Convert requirements.txt to pyproject.toml
License: Apache-2.0
Keywords: poetry,pyproject,toml,requirements,convert
Author: Chattr
Author-email: chattr23@gmail.com
Requires-Python: >=3.8.1,<4.0.0
Classifier: Development Status :: 5 - Production/Stable
Classifier: Intended Audience :: Developers
Classifier: Intended Audience :: Science/Research
Classifier: License :: OSI Approved :: Apache Software License
Classifier: Programming Language :: Python :: 3
Classifier: Programming Language :: Python :: 3.10
Classifier: Programming Language :: Python :: 3.6
Classifier: Programming Language :: Python :: 3.7
Classifier: Programming Language :: Python :: 3.8
Classifier: Programming Language :: Python :: 3.9
Requires-Dist: click (==8.1.3)
